{
  "summary":{
    "window_days":30,
    "players_processed":20,
    "games_processed":656,
    "streaks_found":9,
    "counts_by_threshold":{
      "≤5%":7,
      "≤1%":2,
      "≤0.1%":0,
      "≤0.01%":0
    },
    "generated_at":1757273190
  },
  "players":{
    "0blivi0usspy":{
      "username":"0blivi0usspy",
      "title":"GM",
      "avatar":null,
      "max_rating":2931,
      "country":"FR"
    },
    "0gzpanda":{
      "username":"0gzpanda",
      "title":"IM",
      "avatar":"https://images.chesscomfiles.com/uploads/v1/user/73320100.1d4e560c.200x200o.b8fd2b3db995.png",
      "max_rating":3200,
      "country":"US"
    },
    "11kevin":{
      "username":"11kevin",
      "title":"IM",
      "avatar":"https://images.chesscomfiles.com/uploads/v1/user/37593768.3d27d64e.200x200o.d3b1902659a8.jpeg",
      "max_rating":2634,
      "country":"IN"
    },
    "123lt":{
      "username":"123lt",
      "title":"GM",
      "avatar":"https://images.chesscomfiles.com/uploads/v1/user/18800602.e26b721f.200x200o.e738019a328a.jpeg",
      "max_rating":2715,
      "country":"CN"
    },
    "124chess":{
      "username":"124chess",
      "title":"GM",
      "avatar":"https://images.chesscomfiles.com/uploads/v1/user/29499974.39041f89.200x200o.f6478a5ae8e2.jpeg",
      "max_rating":2764,
      "country":"RU"
    },
    "1977ivan":{
      "username":"1977ivan",
      "title":"GM",
      "avatar":"https://images.chesscomfiles.com/uploads/v1/user/30610578.e05f2196.200x200o.3948baec540a.jpeg",
      "max_rating":2887,
      "country":"RS"
    },
    "1995tiger":{
      "username":"1995tiger",
      "title":"WIM",
      "avatar":"https://images.chesscomfiles.com/uploads/v1/user/32292254.581b9e53.200x200o.63c6e7245230.jpeg",
      "max_rating":2638,
      "country":"ES"
    },
    "1e41-0":{
      "username":"1e41-0",
      "title":"IM",
      "avatar":"https://images.chesscomfiles.com/uploads/v1/user/24318588.5e8b59f5.200x200o.d8d0c5a05d32.jpeg",
      "max_rating":3018,
      "country":"US"
    },
    "1nikolachess":{
      "username":"1nikolachess",
      "title":"IM",
      "avatar":null,
      "max_rating":2394,
      "country":"BG"
    },
    "1scaramouche1":{
      "username":"1scaramouche1",
      "title":"IM",
      "avatar":"https://images.chesscomfiles.com/uploads/v1/user/4739356.7abd41f4.200x200o.c5500e2c4a2d.jpeg",
      "max_rating":2237,
      "country":"US"
    },
    "1stsecond":{
      "username":"1stsecond",
      "title":"GM",
      "avatar":"https://images.chesscomfiles.com/uploads/v1/user/13013662.ad4c23f8.200x200o.da161572d8ed.jpeg",
      "max_rating":2971,
      "country":"LV"
    },
    "2bf41-0":{
      "username":"2bf41-0",
      "title":"GM",
      "avatar":"https://images.chesscomfiles.com/uploads/v1/user/28618754.1032a77c.200x200o.b608b829628b.jpg",
      "max_rating":2926,
      "country":"US"
    },
    "2krk1":{
      "username":"2krk1",
      "title":"IM",
      "avatar":null,
      "max_rating":2842,
      "country":"ES"
    },
    "2ktngo":{
      "username":"2ktngo",
      "title":"IM",
      "avatar":null,
      "max_rating":2576,
      "country":"US"
    },
    "3f32":{
      "username":"3f32",
      "title":"IM",
      "avatar":null,
      "max_rating":2741,
      "country":"IL"
    },
    "4empechement":{
      "username":"4empechement",
      "title":"WGM",
      "avatar":null,
      "max_rating":2522,
      "country":"HU"
    },
    "60minban":{
      "username":"60minban",
      "title":"IM",
      "avatar":null,
      "max_rating":2889,
      "country":"US"
    },
    "6packplayer":{
      "username":"6packplayer",
      "title":"IM",
      "avatar":"https://images.chesscomfiles.com/uploads/v1/user/279211437.1d16fce6.200x200o.1ba4e98af25d.jpg",
      "max_rating":2555,
      "country":"PL"
    },
    "72hitman72":{
      "username":"72hitman72",
      "title":"IM",
      "avatar":null,
      "max_rating":2276,
      "country":"NL"
    },
    "777azazello777":{
      "username":"777azazello777",
      "title":"GM",
      "avatar":null,
      "max_rating":null,
      "country":"PT"
    }
  },
  "interesting_streaks":[
    {
      "username":"1e41-0",
      "player_title":"IM",
      "player_max_rating":3018,
      "streak":{
        "length":8,
        "prob":0.029563828774052302,
        "threshold":"≤5%",
        "start_time":1756436994,
        "end_time":1756825317,
        "games":[
          {
            "end_time":1756436994,
            "rules":"chess",
            "time_class":"blitz",
            "opponent":{
              "username":"shyam",
              "rating":2833
            },
            "winner_rating":3005,
            "p_win":0.7210358999625037,
            "url":"https://www.chess.com/game/live/142462211318"
          },
          {
            "end_time":1756447996,
            "rules":"chess",
            "time_class":"blitz",
            "opponent":{
              "username":"OTSz",
              "rating":2847
            },
            "winner_rating":3010,
            "p_win":0.7141730073904023,
            "url":"https://www.chess.com/game/live/142465942246"
          },
          {
            "end_time":1756448277,
            "rules":"chess",
            "time_class":"blitz",
            "opponent":{
              "username":"NigelShort",
              "rating":2859
            },
            "winner_rating":3015,
            "p_win":0.7064478495407309,
            "url":"https://www.chess.com/game/live/142466062252"
          },
          {
            "end_time":1756449702,
            "rules":"chess",
            "time_class":"blitz",
            "opponent":{
              "username":"Daffidollchess2",
              "rating":2932
            },
            "winner_rating":3021,
            "p_win":0.6198431858335149,
            "url":"https://www.chess.com/game/live/142466580170"
          },
          {
            "end_time":1756509272,
            "rules":"chess",
            "time_class":"blitz",
            "opponent":{
              "username":"ManuDavid2910",
              "rating":2972
            },
            "winner_rating":3028,
            "p_win":0.5734358936271385,
            "url":"https://www.chess.com/game/live/142498033736"
          },
          {
            "end_time":1756509524,
            "rules":"chess",
            "time_class":"blitz",
            "opponent":{
              "username":"ManuDavid2910",
              "rating":2965
            },
            "winner_rating":3035,
            "p_win":0.593121757784753,
            "url":"https://www.chess.com/game/live/142498131168"
          },
          {
            "end_time":1756824489,
            "rules":"chess",
            "time_class":"blitz",
            "opponent":{
              "username":"kuli4ik",
              "rating":3012
            },
            "winner_rating":3043,
            "p_win":0.5373201451643821,
            "url":"https://www.chess.com/game/live/142638865474"
          },
          {
            "end_time":1756825317,
            "rules":"chess",
            "time_class":"blitz",
            "opponent":{
              "username":"dzhumagaliev",
              "rating":2882
            },
            "winner_rating":3048,
            "p_win":0.7174250993037916,
            "url":"https://www.chess.com/game/live/142639369162"
          }
        ]
      }
    },
    {
      "username":"0blivi0usspy",
      "player_title":"GM",
      "player_max_rating":2931,
      "streak":{
        "length":6,
        "prob":0.0041492947296964825,
        "threshold":"≤1%",
        "start_time":1756817172,
        "end_time":1756819573,
        "games":[
          {
            "end_time":1756817172,
            "rules":"chess",
            "time_class":"bullet",
            "opponent":{
              "username":"gospodarsaha07",
              "rating":2730
            },
            "winner_rating":2756,
            "p_win":0.5297161520506017,
            "url":"https://www.chess.com/game/live/142634571730"
          },
          {
            "end_time":1756817291,
            "rules":"chess",
            "time_class":"bullet",
            "opponent":{
              "username":"remi04",
              "rating":2917
            },
            "winner_rating":2768,
            "p_win":0.29016362785882915,
            "url":"https://www.chess.com/game/live/142634622926"
          },
          {
            "end_time":1756817321,
            "rules":"chess",
            "time_class":"bullet",
            "opponent":{
              "username":"remi04",
              "rating":2906
            },
            "winner_rating":2779,
            "p_win":0.3170321476648914,
            "url":"https://www.chess.com/game/live/142634679240"
          },
          {
            "end_time":1756817475,
            "rules":"chess",
            "time_class":"bullet",
            "opponent":{
              "username":"Gusto_Frutta",
              "rating":2756
            },
            "winner_rating":2787,
            "p_win":0.5367619389627358,
            "url":"https://www.chess.com/game/live/142634709174"
          },
          {
            "end_time":1756819412,
            "rules":"chess",
            "time_class":"bullet",
            "opponent":{
              "username":"remi04",
              "rating":2872
            },
            "winner_rating":2797,
            "p_win":0.38541679180701294,
            "url":"https://www.chess.com/game/live/142635861578"
          },
          {
            "end_time":1756819573,
            "rules":"chess",
            "time_class":"bullet",
            "opponent":{
              "username":"Toxicmybrother",
              "rating":2863
            },
            "winner_rating":2807,
            "p_win":0.41159723487392774,
            "url":"https://www.chess.com/game/live/142635946636"
          }
        ]
      }
    },
    {
      "username":"0blivi0usspy",
      "player_title":"GM",
      "player_max_rating":2931,
      "streak":{
        "length":6,
        "prob":0.022038959832744495,
        "threshold":"≤5%",
        "start_time":1755285620,
        "end_time":1755361359,
        "games":[
          {
            "end_time":1755285620,
            "rules":"chess",
            "time_class":"blitz",
            "opponent":{
              "username":"EddieMarsalla",
              "rating":2906
            },
            "winner_rating":2910,
            "p_win":0.4988521400804602,
            "url":"https://www.chess.com/game/live/141926855924"
          },
          {
            "end_time":1755285788,
            "rules":"chess",
            "time_class":"blitz",
            "opponent":{
              "username":"valorant64",
              "rating":2921
            },
            "winner_rating":2918,
            "p_win":0.490306294898846,
            "url":"https://www.chess.com/game/live/141927027814"
          },
          {
            "end_time":1755286259,
            "rules":"chess",
            "time_class":"blitz",
            "opponent":{
              "username":"Kaufman_David",
              "rating":2899
            },
            "winner_rating":2926,
            "p_win":0.5323044910995045,
            "url":"https://www.chess.com/game/live/141927185088"
          },
          {
            "end_time":1755286604,
            "rules":"chess",
            "time_class":"blitz",
            "opponent":{
              "username":"Kaufman_David",
              "rating":2892
            },
            "winner_rating":2933,
            "p_win":0.5524077101876806,
            "url":"https://www.chess.com/game/live/141927356448"
          },
          {
            "end_time":1755361196,
            "rules":"chess",
            "time_class":"blitz",
            "opponent":{
              "username":"NewBornNow",
              "rating":2933
            },
            "winner_rating":2941,
            "p_win":0.5048631072648914,
            "url":"https://www.chess.com/game/live/141960209564"
          },
          {
            "end_time":1755361359,
            "rules":"chess",
            "time_class":"blitz",
            "opponent":{
              "username":"only_strong_moves",
              "rating":2868
            },
            "winner_rating":2947,
            "p_win":0.606957506336639,
            "url":"https://www.chess.com/game/live/141960445448"
          }
        ]
      }
    },
    {
      "username":"2krk1",
      "player_title":"IM",
      "player_max_rating":2842,
      "streak":{
        "length":7,
        "prob":0.007907418128427412,
        "threshold":"≤1%",
        "start_time":1755109950,
        "end_time":1755112231,
        "games":[
          {
            "end_time":1755109950,
            "rules":"chess",
            "time_class":"blitz",
            "opponent":{
              "username":"StellarChess",
              "rating":2730
            },
            "winner_rating":2735,
            "p_win":0.5028210472397802,
            "url":"https://www.chess.com/game/live/141844315496"
          },
          {
            "end_time":1755110304,
            "rules":"chess",
            "time_class":"blitz",
            "opponent":{
              "username":"StellarChess",
              "rating":2722
            },
            "winner_rating":2743,
            "p_win":0.5259029021808316,
            "url":"https://www.chess.com/game/live/141844453372"
          },
          {
            "end_time":1755110681,
            "rules":"chess",
            "time_class":"blitz",
            "opponent":{
              "username":"Vinnkratos",
              "rating":2702
            },
            "winner_rating":2750,
            "p_win":0.5612877592301021,
            "url":"https://www.chess.com/game/live/141844663956"
          },
          {
            "end_time":1755110900,
            "rules":"chess",
            "time_class":"blitz",
            "opponent":{
              "username":"Vinnkratos",
              "rating":2695
            },
            "winner_rating":2757,
            "p_win":0.5811390932335521,
            "url":"https://www.chess.com/game/live/141844869904"
          },
          {
            "end_time":1755111254,
            "rules":"chess",
            "time_class":"blitz",
            "opponent":{
              "username":"Vinnkratos",
              "rating":2688
            },
            "winner_rating":2764,
            "p_win":0.6007270512169084,
            "url":"https://www.chess.com/game/live/141844994028"
          },
          {
            "end_time":1755111587,
            "rules":"chess",
            "time_class":"blitz",
            "opponent":{
              "username":"Vinnkratos",
              "rating":2682
            },
            "winner_rating":2770,
            "p_win":0.6172626321287306,
            "url":"https://www.chess.com/game/live/141845193180"
          },
          {
            "end_time":1755112231,
            "rules":"chess",
            "time_class":"blitz",
            "opponent":{
              "username":"Yaacovn",
              "rating":2972
            },
            "winner_rating":2782,
            "p_win":0.24723095725596814,
            "url":"https://www.chess.com/game/live/141845521436"
          }
        ]
      }
    },
    {
      "username":"2krk1",
      "player_title":"IM",
      "player_max_rating":2842,
      "streak":{
        "length":6,
        "prob":0.014657110694076398,
        "threshold":"≤5%",
        "start_time":1754733123,
        "end_time":1754750975,
        "games":[
          {
            "end_time":1754733123,
            "rules":"chess",
            "time_class":"blitz",
            "opponent":{
              "username":"JoeAssaad",
              "rating":2760
            },
            "winner_rating":2760,
            "p_win":0.49560078754879566,
            "url":"https://www.chess.com/game/live/141667660424"
          },
          {
            "end_time":1754733404,
            "rules":"chess",
            "time_class":"blitz",
            "opponent":{
              "username":"JoeAssaad",
              "rating":2752
            },
            "winner_rating":2768,
            "p_win":0.5186971393159643,
            "url":"https://www.chess.com/game/live/141667841742"
          },
          {
            "end_time":1754738104,
            "rules":"chess",
            "time_class":"blitz",
            "opponent":{
              "username":"Chessmood_Warrior",
              "rating":2807
            },
            "winner_rating":2777,
            "p_win":0.45224254237551664,
            "url":"https://www.chess.com/game/live/141670108354"
          },
          {
            "end_time":1754738476,
            "rules":"chess",
            "time_class":"blitz",
            "opponent":{
              "username":"Chessmood_Warrior",
              "rating":2798
            },
            "winner_rating":2786,
            "p_win":0.47810651101140766,
            "url":"https://www.chess.com/game/live/141670288096"
          },
          {
            "end_time":1754739366,
            "rules":"chess",
            "time_class":"blitz",
            "opponent":{
              "username":"icecreamiscream",
              "rating":2814
            },
            "winner_rating":2795,
            "p_win":0.46783824110981864,
            "url":"https://www.chess.com/game/live/141670773962"
          },
          {
            "end_time":1754750975,
            "rules":"chess",
            "time_class":"blitz",
            "opponent":{
              "username":"UmanWdd",
              "rating":2754
            },
            "winner_rating":2802,
            "p_win":0.5636515906243389,
            "url":"https://www.chess.com/game/live/141677260538"
          }
        ]
      }
    },
    {
      "username":"2krk1",
      "player_title":"IM",
      "player_max_rating":2842,
      "streak":{
        "length":5,
        "prob":0.023873177853833492,
        "threshold":"≤5%",
        "start_time":1757035711,
        "end_time":1757078410,
        "games":[
          {
            "end_time":1757035711,
            "rules":"chess",
            "time_class":"blitz",
            "opponent":{
              "username":"StrategySensei007",
              "rating":2726
            },
            "winner_rating":2714,
            "p_win":0.47586621437889803,
            "url":"https://www.chess.com/game/live/142738340644"
          },
          {
            "end_time":1757035938,
            "rules":"chess",
            "time_class":"blitz",
            "opponent":{
              "username":"StrategySensei007",
              "rating":2718
            },
            "winner_rating":2722,
            "p_win":0.49899582130580045,
            "url":"https://www.chess.com/game/live/142738444488"
          },
          {
            "end_time":1757036182,
            "rules":"chess",
            "time_class":"blitz",
            "opponent":{
              "username":"StrategySensei007",
              "rating":2710
            },
            "winner_rating":2730,
            "p_win":0.5221295759958217,
            "url":"https://www.chess.com/game/live/142738517646"
          },
          {
            "end_time":1757064813,
            "rules":"chess",
            "time_class":"blitz",
            "opponent":{
              "username":"GMG",
              "rating":2815
            },
            "winner_rating":2740,
            "p_win":0.3888082125677196,
            "url":"https://www.chess.com/game/live/142749434806"
          },
          {
            "end_time":1757078410,
            "rules":"chess",
            "time_class":"blitz",
            "opponent":{
              "username":"Lemmingsplayer",
              "rating":2748
            },
            "winner_rating":2748,
            "p_win":0.4952388754682818,
            "url":"https://www.chess.com/game/live/142756981502"
          }
        ]
      }
    },
    {
      "username":"2krk1",
      "player_title":"IM",
      "player_max_rating":2842,
      "streak":{
        "length":5,
        "prob":0.03665443510028382,
        "threshold":"≤5%",
        "start_time":1756476538,
        "end_time":1756480854,
        "games":[
          {
            "end_time":1756476538,
            "rules":"chess",
            "time_class":"blitz",
            "opponent":{
              "username":"mw86",
              "rating":2711
            },
            "winner_rating":2735,
            "p_win":0.5303849179005804,
            "url":"https://www.chess.com/game/live/142480045462"
          },
          {
            "end_time":1756476922,
            "rules":"chess",
            "time_class":"blitz",
            "opponent":{
              "username":"mw86",
              "rating":2704
            },
            "winner_rating":2742,
            "p_win":0.5504632186953439,
            "url":"https://www.chess.com/game/live/142480276698"
          },
          {
            "end_time":1756477308,
            "rules":"chess",
            "time_class":"blitz",
            "opponent":{
              "username":"mw86",
              "rating":2697
            },
            "winner_rating":2749,
            "p_win":0.570377027876097,
            "url":"https://www.chess.com/game/live/142480523930"
          },
          {
            "end_time":1756478370,
            "rules":"chess",
            "time_class":"blitz",
            "opponent":{
              "username":"moroccanchess23",
              "rating":2811
            },
            "winner_rating":2759,
            "p_win":0.4215162259380698,
            "url":"https://www.chess.com/game/live/142481254086"
          },
          {
            "end_time":1756480854,
            "rules":"chess",
            "time_class":"blitz",
            "opponent":{
              "username":"padam19",
              "rating":2749
            },
            "winner_rating":2767,
            "p_win":0.5221926282961091,
            "url":"https://www.chess.com/game/live/142482983394"
          }
        ]
      }
    },
    {
      "username":"2krk1",
      "player_title":"IM",
      "player_max_rating":2842,
      "streak":{
        "length":5,
        "prob":0.039170816130754106,
        "threshold":"≤5%",
        "start_time":1756398472,
        "end_time":1756401604,
        "games":[
          {
            "end_time":1756398472,
            "rules":"chess",
            "time_class":"blitz",
            "opponent":{
              "username":"Deeper44",
              "rating":2702
            },
            "winner_rating":2720,
            "p_win":0.522051613087299,
            "url":"https://www.chess.com/game/live/142444962924"
          },
          {
            "end_time":1756398849,
            "rules":"chess",
            "time_class":"blitz",
            "opponent":{
              "username":"Deeper44",
              "rating":2694
            },
            "winner_rating":2728,
            "p_win":0.5450391766270525,
            "url":"https://www.chess.com/game/live/142445172374"
          },
          {
            "end_time":1756399216,
            "rules":"chess",
            "time_class":"blitz",
            "opponent":{
              "username":"Deeper44",
              "rating":2687
            },
            "winner_rating":2735,
            "p_win":0.5649991367236435,
            "url":"https://www.chess.com/game/live/142445407856"
          },
          {
            "end_time":1756400883,
            "rules":"chess",
            "time_class":"blitz",
            "opponent":{
              "username":"Fivetrick",
              "rating":2783
            },
            "winner_rating":2744,
            "p_win":0.4359815024756869,
            "url":"https://www.chess.com/game/live/142446423074"
          },
          {
            "end_time":1756401604,
            "rules":"chess",
            "time_class":"blitz",
            "opponent":{
              "username":"RafaelVaganian",
              "rating":2707
            },
            "winner_rating":2751,
            "p_win":0.5588633251369527,
            "url":"https://www.chess.com/game/live/142446877256"
          }
        ]
      }
    },
    {
      "username":"2krk1",
      "player_title":"IM",
      "player_max_rating":2842,
      "streak":{
        "length":4,
        "prob":0.04915066071170567,
        "threshold":"≤5%",
        "start_time":1756652687,
        "end_time":1756654131,
        "games":[
          {
            "end_time":1756652687,
            "rules":"chess",
            "time_class":"blitz",
            "opponent":{
              "username":"dedpihto_v_kozhanom_palto",
              "rating":2802
            },
            "winner_rating":2731,
            "p_win":0.391671114325364,
            "url":"https://www.chess.com/game/live/142560622420"
          },
          {
            "end_time":1756653032,
            "rules":"chess",
            "time_class":"blitz",
            "opponent":{
              "username":"aliba25",
              "rating":2768
            },
            "winner_rating":2740,
            "p_win":0.4536069777432124,
            "url":"https://www.chess.com/game/live/142560848778"
          },
          {
            "end_time":1756653659,
            "rules":"chess",
            "time_class":"blitz",
            "opponent":{
              "username":"Lemmingsplayer",
              "rating":2728
            },
            "winner_rating":2748,
            "p_win":0.5241095638896561,
            "url":"https://www.chess.com/game/live/142561249430"
          },
          {
            "end_time":1756654131,
            "rules":"chess",
            "time_class":"blitz",
            "opponent":{
              "username":"Jarming",
              "rating":2733
            },
            "winner_rating":2756,
            "p_win":0.5278445056488288,
            "url":"https://www.chess.com/game/live/142561528834"
          }
        ]
      }
    }
  ]
}